{
    "nombreApp" : "America Precolombina",
    "rutas"     : [
        {
            "ruta"  : "incas",
            "icon"  : "incas",
            "texto" : "incas"
        },
        {
            "ruta"  : "mayas",
            "icon"  : "mayas",
            "texto" : "mayas"
        },
        {
            "ruta"  : "aztecas",
            "icon"  : "aztecas",
            "texto" : "Aztecas"
        }        
    ],
    "carpetas"  : [
        {
            "ruta"  : "aztecasUbicacion",
            "icon"  : "ubicacion",
            "texto" : "Ubicación"
        }
    ]
}